bonicbot/__init__.py
bonicbot/controller.py
bonicbot/test_installation.py
bonicbot-2.0.1.dist-info/licenses/LICENCE
bonicbot-2.0.1.dist-info/METADATA
bonicbot-2.0.1.dist-info/WHEEL
bonicbot-2.0.1.dist-info/entry_points.txt
bonicbot-2.0.1.dist-info/top_level.txt
bonicbot-2.0.1.dist-info/RECORD
