Metadata-Version: 2.4
Name: bonicbot
Version: 2.0.1
Summary: Python library for controlling BonicBot humanoid robot via serial communication and WebSocket
Home-page: https://github.com/Autobonics/bonicbot
Author: Shahir Abdulla
Author-email: Shahir Abdulla <shahir@autobonics.com>
Maintainer-email: Shahir Abdulla <shahir@autobonics.com>
License: MIT
Project-URL: Homepage, https://github.com/Autobonics/bonicbot
Project-URL: Documentation, https://github.com/Autobonics/bonicbot/docs
Project-URL: Repository, https://github.com/Autobonics/bonicbot.git
Project-URL: Bug Tracker, https://github.com/Autobonics/bonicbot/issues
Keywords: robot,robotics,servo,control,serial,communication,humanoid,bonicbot,hardware,automation,websocket,remote
Classifier: Development Status :: 4 - Beta
Classifier: Intended Audience :: Developers
Classifier: Intended Audience :: Education
Classifier: Intended Audience :: Science/Research
Classifier: Topic :: Scientific/Engineering :: Human Machine Interfaces
Classifier: Topic :: Software Development :: Libraries :: Python Modules
Classifier: Topic :: System :: Hardware :: Hardware Drivers
Classifier: License :: OSI Approved :: MIT License
Classifier: Programming Language :: Python :: 3
Classifier: Programming Language :: Python :: 3.7
Classifier: Programming Language :: Python :: 3.8
Classifier: Programming Language :: Python :: 3.9
Classifier: Programming Language :: Python :: 3.10
Classifier: Programming Language :: Python :: 3.11
Classifier: Programming Language :: Python :: 3.12
Classifier: Programming Language :: Python :: 3.13
Classifier: Operating System :: OS Independent
Requires-Python: >=3.7
License-File: LICENCE
Requires-Dist: pyserial>=3.4
Requires-Dist: websockets>=15.0
Provides-Extra: gui
Provides-Extra: dev
Requires-Dist: pytest>=6.0; extra == "dev"
Requires-Dist: pytest-cov; extra == "dev"
Requires-Dist: black; extra == "dev"
Requires-Dist: flake8; extra == "dev"
Requires-Dist: mypy; extra == "dev"
Dynamic: author
Dynamic: home-page
Dynamic: license-file
Dynamic: requires-python
